PyDrocsid/__init__.py
PyDrocsid/async_thread.py
PyDrocsid/cog.py
PyDrocsid/command.py
PyDrocsid/command_edit.py
PyDrocsid/config.py
PyDrocsid/converter.py
PyDrocsid/database/__init__.py
PyDrocsid/database/database.py
PyDrocsid/discohook.py
PyDrocsid/embeds.py
PyDrocsid/emoji_map.json
PyDrocsid/emojis.py
PyDrocsid/environment.py
PyDrocsid/events.py
PyDrocsid/github_api.py
PyDrocsid/logger.py
PyDrocsid/material_colors.py
PyDrocsid/material_colors.yml
PyDrocsid/multilock.py
PyDrocsid/pagination.py
PyDrocsid/permission.py
PyDrocsid/prefix.py
PyDrocsid/pubsub.py
PyDrocsid/redis.py
PyDrocsid/settings.py
PyDrocsid/translations/en.yml
PyDrocsid/translations.py
PyDrocsid/util.py
pydrocsid-2.3.4.dist-info/LICENSE
pydrocsid-2.3.4.dist-info/WHEEL
pydrocsid-2.3.4.dist-info/METADATA
pydrocsid-2.3.4.dist-info/RECORD
