Metadata-Version: 2.1
Name: pydrocsid
Version: 2.3.4
Summary: Python Discord Bot Framework based on pycord
Home-page: https://github.com/PyDrocsid/library
License: GPL-3.0-only
Author: Defelo
Author-email: elodef42@gmail.com
Requires-Python: >=3.10,<4.0
Classifier: License :: OSI Approved :: GNU General Public License v3 (GPLv3)
Classifier: Programming Language :: Python :: 3
Classifier: Programming Language :: Python :: 3.10
Requires-Dist: PyYAML (>=6.0,<7.0)
Requires-Dist: SQLAlchemy (>=1.4.32,<2.0.0)
Requires-Dist: aenum (>=3.1.8,<4.0.0)
Requires-Dist: aiohttp (>=3.8.1,<4.0.0)
Requires-Dist: aiomysql (>=0.1.1,<0.2.0)
Requires-Dist: aioredis (>=2.0.1,<3.0.0)
Requires-Dist: asyncpg (>=0.25.0,<0.26.0)
Requires-Dist: httpx (>=0.23.0,<0.24.0)
Requires-Dist: py-cord (>=2.0.0,<3.0.0)
Requires-Dist: sentry-sdk (>=1.5.12,<2.0.0)
Project-URL: Repository, https://github.com/PyDrocsid/library
